flask_signing/__init__.py
flask_signing/__metadata__.py
tests/__init__.py
tests/performance_tests.py
flask_signing-0.9.0.dist-info/LICENSE
flask_signing-0.9.0.dist-info/METADATA
flask_signing-0.9.0.dist-info/WHEEL
flask_signing-0.9.0.dist-info/top_level.txt
flask_signing-0.9.0.dist-info/RECORD
