Metadata-Version: 2.1
Name: flask_signing
Version: 0.9.0
Summary: a signing key extension for flask
Home-page: https://github.com/signebedi/Flask-Signing
Author: Sig Janoska-Bedi
Author-email: signe@atreeus.com
Classifier: Development Status :: 3 - Alpha
Classifier: Intended Audience :: Developers
Classifier: License :: OSI Approved :: BSD License
Classifier: Operating System :: OS Independent
Classifier: Programming Language :: Python :: 3
Classifier: Programming Language :: Python :: 3.7
Classifier: Programming Language :: Python :: 3.8
Classifier: Programming Language :: Python :: 3.9
Classifier: Topic :: Software Development :: Libraries :: Python Modules
License-File: LICENSE
Requires-Dist: Flask <4.0.0
Requires-Dist: Flask-SQLAlchemy <4.0.0
